pybacting/__init__.py
pybacting/__main__.py
pybacting/api.py
pybacting/cli.py
pybacting/display.py
pybacting/io.py
pybacting/version.py
pybacting-0.2.15.dist-info/licenses/LICENSE
pybacting-0.2.15.dist-info/METADATA
pybacting-0.2.15.dist-info/WHEEL
pybacting-0.2.15.dist-info/top_level.txt
pybacting-0.2.15.dist-info/RECORD
